odoo/addons/web_disable_export_group/README.rst
odoo/addons/web_disable_export_group/__init__.py
odoo/addons/web_disable_export_group/__manifest__.py
odoo/addons/web_disable_export_group/i18n/web_disable_export_group.pot
odoo/addons/web_disable_export_group/models/__init__.py
odoo/addons/web_disable_export_group/models/ir_http.py
odoo/addons/web_disable_export_group/readme/CONFIGURE.rst
odoo/addons/web_disable_export_group/readme/CONTRIBUTORS.rst
odoo/addons/web_disable_export_group/readme/DESCRIPTION.rst
odoo/addons/web_disable_export_group/readme/USAGE.rst
odoo/addons/web_disable_export_group/security/groups.xml
odoo/addons/web_disable_export_group/static/description/icon.png
odoo/addons/web_disable_export_group/static/description/index.html
odoo/addons/web_disable_export_group/static/src/js/disable_export_group.js
odoo/addons/web_disable_export_group/templates/assets.xml
odoo11_addon_web_disable_export_group-11.0.1.0.1.dist-info/METADATA
odoo11_addon_web_disable_export_group-11.0.1.0.1.dist-info/WHEEL
odoo11_addon_web_disable_export_group-11.0.1.0.1.dist-info/top_level.txt
odoo11_addon_web_disable_export_group-11.0.1.0.1.dist-info/RECORD
